pysnooper/__init__.py
pysnooper/utils/__init__.py
snooper_ai/__init__.py
snooper_ai/cli.py
snooper_ai/config.py
snooper_ai/pycompat.py
snooper_ai/tracer.py
snooper_ai/utils.py
snooper_ai/variables.py
snooper_ai/llm/__init__.py
snooper_ai/llm/base.py
snooper_ai/llm/claude.py
snooper_ai/llm/openai.py
snooper_ai-0.0.3.dist-info/licenses/AUTHORS
snooper_ai-0.0.3.dist-info/licenses/LICENSE
snooper_ai-0.0.3.dist-info/METADATA
snooper_ai-0.0.3.dist-info/WHEEL
snooper_ai-0.0.3.dist-info/entry_points.txt
snooper_ai-0.0.3.dist-info/top_level.txt
snooper_ai-0.0.3.dist-info/RECORD
