Metadata-Version: 2.4
Name: snooper-ai
Version: 0.0.3
Summary: Debug your Python code with AI assistance
Home-page: https://github.com/alvin-r/snooper-ai
Author: Alvin Ryanputra
Author-email: alvin.ryanputra@gmail.com
Classifier: Environment :: Console
Classifier: Programming Language :: Python :: 3
Classifier: Programming Language :: Python :: 3.7
Classifier: Programming Language :: Python :: 3.8
Classifier: Programming Language :: Python :: 3.9
Classifier: Programming Language :: Python :: 3.10
Classifier: Programming Language :: Python :: 3.11
Classifier: License :: OSI Approved :: MIT License
Classifier: Operating System :: OS Independent
Requires-Python: >=3.7
License-File: LICENSE
License-File: AUTHORS
Requires-Dist: anthropic>=0.18.0
Requires-Dist: click>=8.1.7
Requires-Dist: rich>=13.7.0
Requires-Dist: openai>=1.12.0
Requires-Dist: tomlkit>=0.12.4
Provides-Extra: tests
Requires-Dist: pytest; extra == "tests"
Dynamic: author
Dynamic: author-email
Dynamic: classifier
Dynamic: description
Dynamic: description-content-type
Dynamic: home-page
Dynamic: license-file
Dynamic: provides-extra
Dynamic: requires-dist
Dynamic: requires-python
Dynamic: summary
